CHANGELOG
Makefile
README
requirements-twisted.txt
requirements.txt
setup.cfg
setup.py
beanstalk/__init__.py
beanstalk/_libeventconn.py
beanstalk/errors.py
beanstalk/job.py
beanstalk/multiserverconn.py
beanstalk/protohandler.py
beanstalk/serverconn.py
beanstalk/twisted_client.py
docs/CREDITS
docs/LICENSE
examples/libevent_main.py
examples/simple_clients.py
examples/twisted_consumer.py
examples/twisted_producer.py
pybeanstalk.egg-info/PKG-INFO
pybeanstalk.egg-info/SOURCES.txt
pybeanstalk.egg-info/dependency_links.txt
pybeanstalk.egg-info/not-zip-safe
pybeanstalk.egg-info/requires.txt
pybeanstalk.egg-info/top_level.txt
tests/config.py
tests/test_MultiServerConn.py
tests/test_Proto.py
tests/test_ServerConn.py
tests/test_Twisted.py
tests/test_errors.py
tests/tests.cfg