Metadata-Version: 1.1
Name: pybeanstalk
Version: 1.0rc1
Summary: A python client library for beanstalkd.
Home-page: https://github.com/beanstalkd/pybeanstalk
Author: Erich Heine
Author-email: sophacles@gmail.com
License: UNKNOWN
Keywords: beanstalkd,twisted
Platform: UNKNOWN
Classifier: Development Status :: 4 - Beta
Classifier: Intended Audience :: Developers
Classifier: License :: OSI Approved :: BSD License
Classifier: License :: OSI Approved :: GNU General Public License (GPL)
Classifier: Natural Language :: English
Classifier: Operating System :: MacOS :: MacOS X
Classifier: Operating System :: POSIX
Classifier: Programming Language :: Python
Classifier: Topic :: Communications
Classifier: Topic :: Internet
Classifier: Topic :: Scientific/Engineering
Classifier: Topic :: Software Development :: Libraries
Classifier: Topic :: Software Development :: Object Brokering
Classifier: Topic :: System
